{"cameraMode":{"drawMode":0,"name":"Shaded","section":"Shading Mode"},"sceneLighting":true,"audioPlay":false,"sceneViewState":{"m_AlwaysRefresh":false,"showFog":true,"showSkybox":true,"showFlares":true,"showImageEffects":true,"showParticleSystems":true,"showVisualEffectGraphs":true,"m_FxEnabled":true},"in2DMode":false,"pivot":{"x":-3.512622117996216,"y":-0.1212071031332016,"z":-0.4509775936603546},"rotation":{"x":-0.09604521840810776,"y":0.7105739712715149,"z":-0.09891045838594437,"w":-0.6899848580360413},"size":3.162891387939453,"orthographic":false}